svo/__init__.py
svo/core.py
svo/__metadata__/DISCLIAIMER.md
svo/__metadata__/LICENSE
svo/__metadata__/README.md
svo/__metadata__/__init__.py
svo/__metadata__/requirements.txt
svo/pkg_data/data.json
svo-0.0.4.dist-info/METADATA
svo-0.0.4.dist-info/WHEEL
svo-0.0.4.dist-info/top_level.txt
svo-0.0.4.dist-info/RECORD
